{"images/amazingmeeting.png":["images/amazingmeeting.png"],"images/anna.png":["images/anna.png"],"images/bananasplit.png":["images/bananasplit.png"],"images/bentcowgirl.png":["images/bentcowgirl.png"],"images/breeze.png":["images/breeze.png"],"images/bung.png":["images/bung.png"],"images/butterfly.png":["images/butterfly.png"],"images/captivity.png":["images/captivity.png"],"images/carmechanic.png":["images/carmechanic.png"],"images/cat.png":["images/cat.png"],"images/chairman.png":["images/chairman.png"],"images/comfortableplace.png":["images/comfortableplace.png"],"images/cowgirl.png":["images/cowgirl.png"],"images/deckchair.png":["images/deckchair.png"],"images/descent.png":["images/descent.png"],"images/dirtydancing.png":["images/dirtydancing.png"],"images/doggyontheedge.png":["images/doggyontheedge.png"],"images/dragon.png":["images/dragon.png"],"images/eagle.png":["images/eagle.png"],"images/facesitting.png":["images/facesitting.png"],"images/foreplay.jpg":["images/foreplay.jpg"],"images/ghetto.png":["images/ghetto.png"],"images/gimlet.png":["images/gimlet.png"],"images/goddess.png":["images/goddess.png"],"images/gorge.png":["images/gorge.png"],"images/grasshopper.png":["images/grasshopper.png"],"images/harp.png":["images/harp.png"],"images/hatter.jpg":["images/hatter.jpg"],"images/hatter2.png":["images/hatter2.png"],"images/hatter3.jpg":["images/hatter3.jpg"],"images/hatter4.png":["images/hatter4.png"],"images/hood.png":["images/hood.png"],"images/horizon.png":["images/horizon.png"],"images/hunger.png":["images/hunger.png"],"images/inventive69.png":["images/inventive69.png"],"images/jamaicancocktail.png":["images/jamaicancocktail.png"],"images/knight.png":["images/knight.png"],"images/launchpad.png":["images/launchpad.png"],"images/legsonshoulder.png":["images/legsonshoulder.png"],"images/lickingmaster.png":["images/lickingmaster.png"],"images/louise.png":["images/louise.png"],"images/lowdoggy.png":["images/lowdoggy.png"],"images/magicmountain.png":["images/magicmountain.png"],"images/mast.png":["images/mast.png"],"images/merger.png":["images/merger.png"],"images/mirage.png":["images/mirage.png"],"images/missionary.gif":["images/missionary.gif"],"images/missionary.png":["images/missionary.png"],"images/moonlight.png":["images/moonlight.png"],"images/pearl.png":["images/pearl.png"],"images/pendant.png":["images/pendant.png"],"images/pisces.png":["images/pisces.png"],"images/plank.png":["images/plank.png"],"images/pleasurebible.png":["images/pleasurebible.png"],"images/pretzel.png":["images/pretzel.png"],"images/raretrick.png":["images/raretrick.png"],"images/recharge.png":["images/recharge.png"],"images/reversecowgirl.png":["images/reversecowgirl.png"],"images/screw.png":["images/screw.png"],"images/seashell.png":["images/seashell.png"],"images/shell.png":["images/shell.png"],"images/shining.png":["images/shining.png"],"images/slope.png":["images/slope.png"],"images/snail.png":["images/snail.png"],"images/snakecharmer.png":["images/snakecharmer.png"],"images/source.png":["images/source.png"],"images/spanishguitar.png":["images/spanishguitar.png"],"images/sphinx.png":["images/sphinx.png"],"images/spicydish.png":["images/spicydish.png"],"images/splittingbamboo.png":["images/splittingbamboo.png"],"images/spoon.png":["images/spoon.png"],"images/spreadeagle.png":["images/spreadeagle.png"],"images/superhero.png":["images/superhero.png"],"images/superwomen.png":["images/superwomen.png"],"images/szajhatter.jpg":["images/szajhatter.jpg"],"images/tiramisu.png":["images/tiramisu.png"],"images/tulip.png":["images/tulip.png"],"images/valedictorian.png":["images/valedictorian.png"],"images/virgo.png":["images/virgo.png"],"images/wedge.png":["images/wedge.png"],"images/wrestling.png":["images/wrestling.png"],"images/zeus.png":["images/zeus.png"],"images/zodiac.png":["images/zodiac.png"]}